phxsocket/__init__.py
phxsocket/channel.py
phxsocket/client.py
phxsocket/message.py
phxsocket-0.1.4.dist-info/LICENSE
phxsocket-0.1.4.dist-info/METADATA
phxsocket-0.1.4.dist-info/WHEEL
phxsocket-0.1.4.dist-info/top_level.txt
phxsocket-0.1.4.dist-info/RECORD
