Metadata-Version: 2.1
Name: phxsocket
Version: 0.1.4
Summary: Websocket client for Phoenix Elixir
Home-page: https://github.com/wwww-wwww/phxsocket
Author: wwwwwwww
Author-email: wvvwvvvvwvvw@gmail.com
Classifier: Programming Language :: Python :: 3
Classifier: License :: OSI Approved :: GNU General Public License v3 (GPLv3)
Classifier: Operating System :: OS Independent
Requires-Python: >=3.10
License-File: LICENSE
Requires-Dist: websockets (>=8.1)
